<?xml version="1.0" encoding="UTF-8"?>
<templateSet group="Zen CSS">
  <template name="bdt" value="border-top:$VAR0$;" description="border-top:...;" toReformat="true" toShortenFQNames="true">
    <variable name="VAR0" expression="" defaultValue="&quot;&quot;" alwaysStopAt="true" />
    <context>
      <option name="CSS" value="false" />
      <option name="HTML_TEXT" value="true" />
      <option name="HTML" value="false" />
      <option name="XSL_TEXT" value="false" />
      <option name="XML" value="false" />
      <option name="JAVA_SCRIPT" value="false" />
      <option name="JSP" value="false" />
      <option name="SQL" value="false" />
      <option name="PHP" value="false" />
      <option name="HAML" value="false" />
      <option name="OTHER" value="false" />
    </context>
  </template>
</templateSet>

